dbtp/__init__.py
dbtp/asset_defs.py
dbtp/cli/__init__.py
dbtp/cli/constants.py
dbtp/cli/resources.py
dbtp/cli/types.py
dbtp/cli/utils.py
dbtp/dbt_resource.py
dbtp/errors.py
dbtp/py.typed
dbtp/types.py
dbtp/utils.py
dbtp/version.py
dbtp-0.0.2.dist-info/METADATA
dbtp-0.0.2.dist-info/LICENSE
dbtp-0.0.2.dist-info/WHEEL
dbtp-0.0.2.dist-info/RECORD
