Metadata-Version: 2.1
Name: dbtp
Version: 0.0.2
Summary: Run DBT CLI commands in python
Author: Alex Rudolph
Author-email: alex3rudolph@gmail.com
Requires-Python: >=3.8,<4.0
Classifier: Programming Language :: Python :: 3
Classifier: Programming Language :: Python :: 3.8
Classifier: Programming Language :: Python :: 3.9
Classifier: Programming Language :: Python :: 3.10
Classifier: Programming Language :: Python :: 3.11
Requires-Dist: rcheck (>=0.0.7,<0.0.8)
